ometrics/__init__.py
ometrics/aggregate.py
ometrics/io.py
ometrics/metrics.py
ometrics/utils.py
test/__init__.py
test/metrics_test.py
test/nested_dict_test.py
ometrics-1.0.2.dist-info/LICENSE
ometrics-1.0.2.dist-info/METADATA
ometrics-1.0.2.dist-info/WHEEL
ometrics-1.0.2.dist-info/top_level.txt
ometrics-1.0.2.dist-info/RECORD
