Metadata-Version: 2.1
Name: ometrics
Version: 1.0.2
Summary: Metrics aggregation, dumping and loading
Home-page: https://github.com/badryoubiidrissi/ometrics
Author: Badr Youbi Idrissi
Author-email: badryoubiidrissi@gmail.com
License: UNKNOWN
Platform: UNKNOWN
Classifier: Programming Language :: Python :: 3
Classifier: License :: OSI Approved :: MIT License
Classifier: Operating System :: OS Independent
Requires-Python: >=3.6
